LICENSE
fastapi_plan/__init__.py
fastapi_plan/template/cookiecutter.json
fastapi_plan/template/hooks/post_gen_project.py
fastapi_plan/template/{{cookiecutter.project_name}}/.dockerignore
fastapi_plan/template/{{cookiecutter.project_name}}/.env
fastapi_plan/template/{{cookiecutter.project_name}}/.gitignore
fastapi_plan/template/{{cookiecutter.project_name}}/Dockerfile
fastapi_plan/template/{{cookiecutter.project_name}}/aerich.ini
fastapi_plan/template/{{cookiecutter.project_name}}/app/__init__.py
fastapi_plan/template/{{cookiecutter.project_name}}/app/api/__init__.py
fastapi_plan/template/{{cookiecutter.project_name}}/app/api/api.py
fastapi_plan/template/{{cookiecutter.project_name}}/app/api/deps.py
fastapi_plan/template/{{cookiecutter.project_name}}/app/api/routers/__init__.py
fastapi_plan/template/{{cookiecutter.project_name}}/app/api/routers/login.py
fastapi_plan/template/{{cookiecutter.project_name}}/app/api/routers/users.py
fastapi_plan/template/{{cookiecutter.project_name}}/app/core/__init__.py
fastapi_plan/template/{{cookiecutter.project_name}}/app/core/config.py
fastapi_plan/template/{{cookiecutter.project_name}}/app/core/security.py
fastapi_plan/template/{{cookiecutter.project_name}}/app/crud/__init__.py
fastapi_plan/template/{{cookiecutter.project_name}}/app/crud/base.py
fastapi_plan/template/{{cookiecutter.project_name}}/app/crud/crud_user.py
fastapi_plan/template/{{cookiecutter.project_name}}/app/initial.sh
fastapi_plan/template/{{cookiecutter.project_name}}/app/initial_data.py
fastapi_plan/template/{{cookiecutter.project_name}}/app/main.py
fastapi_plan/template/{{cookiecutter.project_name}}/app/migrations/models/0_20210423001328_None.sql
fastapi_plan/template/{{cookiecutter.project_name}}/app/models/__init__.py
fastapi_plan/template/{{cookiecutter.project_name}}/app/models/user.py
fastapi_plan/template/{{cookiecutter.project_name}}/app/schemas/__init__.py
fastapi_plan/template/{{cookiecutter.project_name}}/app/schemas/token.py
fastapi_plan-0.3.2.dist-info/entry_points.txt
fastapi_plan-0.3.2.dist-info/LICENSE
fastapi_plan-0.3.2.dist-info/WHEEL
fastapi_plan-0.3.2.dist-info/METADATA
fastapi_plan-0.3.2.dist-info/RECORD
