Metadata-Version: 2.1
Name: fastapi-plan
Version: 0.3.2
Summary: Dead simple template manager for FastAPI applications
Home-page: https://github.com/rafsaf/fastapi-template
License: MIT
Keywords: Python,FastAPI
Author: rafsaf
Author-email: rafal.safin@rafsaf.pl
Requires-Python: >=3.8,<4.0
Classifier: License :: OSI Approved :: MIT License
Classifier: Programming Language :: Python :: 3
Classifier: Programming Language :: Python :: 3.8
Classifier: Programming Language :: Python :: 3.9
Requires-Dist: cookiecutter (>=1.7.2,<2.0.0)
Project-URL: Repository, https://github.com/rafsaf/fastapi-template
